LICENSE
README.md
setup.py
china_datasets/__init__.py
china_datasets/api.py
china_datasets/backend.py
china_datasets/config.py
china_datasets/repo.py
china_datasets.egg-info/PKG-INFO
china_datasets.egg-info/SOURCES.txt
china_datasets.egg-info/dependency_links.txt
china_datasets.egg-info/entry_points.txt
china_datasets.egg-info/requires.txt
china_datasets.egg-info/top_level.txt
china_datasets/command/__init__.py
china_datasets/command/main.py
china_datasets/command/sync_datasets.py
china_datasets/util/__init__.py
china_datasets/util/configuration.py
china_datasets/util/log.py
china_datasets/util/option.py
china_datasets/util/process.py
china_datasets/util/python.py
china_datasets/util/s3.py
china_datasets/util/thread.py
china_datasets/util/tool.py
china_datasets/util/track.py