Metadata-Version: 2.1
Name: china-datasets
Version: 1.0.0.2
Summary: china-datasets 是一个快速下载中文数据集，处理数据集，精益建模的包。
Home-page: https://github.com/CYang828/china-datasets
Author: CYang
Author-email: zhangchunyang_pri@126.com
License: UNKNOWN
Platform: UNKNOWN
License-File: LICENSE
